<?xml version="1.0" encoding="UTF-8"?>
<objects serializationModel="Studio.02.02.00">
	<object class="AudioFile" id="{b65f694e-9eb4-40a5-9b18-d64a885cb624}">
		<property name="assetPath">
			<value>SFX/StarCollect.mp3</value>
		</property>
		<property name="frequencyInKHz">
			<value>48</value>
		</property>
		<property name="channelCount">
			<value>1</value>
		</property>
		<property name="length">
			<value>1.464</value>
		</property>
		<relationship name="masterAssetFolder">
			<destination>{c48d50d8-0989-4153-9212-aa463022db90}</destination>
		</relationship>
	</object>
</objects>
